basic_deep_learning/__init__.py
basic_deep_learning/functionality/__init__.py
basic_deep_learning/functionality/activations_registry.py
basic_deep_learning/functionality/matrix.py
basic_deep_learning/functionality/setup.py
basic_deep_learning/miscellaneous/__init__.py
basic_deep_learning/miscellaneous/decorators.py
basic_deep_learning/miscellaneous/linear_algebra.py
basic_deep_learning/models/__init__.py
basic_deep_learning/models/mlp.py
basic_deep_learning-0.2.4.dist-info/licenses/LICENSE
basic_deep_learning-0.2.4.dist-info/METADATA
basic_deep_learning-0.2.4.dist-info/WHEEL
basic_deep_learning-0.2.4.dist-info/top_level.txt
basic_deep_learning-0.2.4.dist-info/RECORD
