Metadata-Version: 2.4
Name: basic-deep-learning
Version: 0.2.4
Summary: Simple module for creating deep learning tools, with its own linear algebra and matrices utilities.
Author-email: Diaa Eddine ZAINI <zainidiaaeddine@gmail.com>
License: Copyright (c) 2025 Diaa Eddine ZAINI
Project-URL: Homepage, https://github.com/therealzaini/basic-deep-learning
Project-URL: Documentation, https://basic-deep-learning.readthedocs.io/
Project-URL: Repository, https://github.com/therealzaini/basic-deep-learning
Project-URL: Issues, https://github.com/therealzaini/basic-deep-learning/issues
Keywords: deep learning,machine learning,linear algebra,matrix operations
Classifier: Development Status :: 3 - Alpha
Classifier: Intended Audience :: Education
Classifier: Intended Audience :: Science/Research
Classifier: License :: OSI Approved :: MIT License
Classifier: Programming Language :: Python :: 3
Classifier: Programming Language :: Python :: 3.8
Classifier: Programming Language :: Python :: 3.9
Classifier: Programming Language :: Python :: 3.10
Classifier: Programming Language :: Python :: 3.11
Classifier: Topic :: Scientific/Engineering
Classifier: Topic :: Scientific/Engineering :: Artificial Intelligence
Classifier: Topic :: Software Development :: Libraries :: Python Modules
Requires-Python: >=3.8
License-File: LICENSE
Requires-Dist: matplotlib>=3.5.0
Provides-Extra: docs
Requires-Dist: sphinx; extra == "docs"
Requires-Dist: sphinx_rtd_theme; extra == "docs"
Dynamic: license-file
